{
  "schemaVersion": "5.0.0",
  "generatedAt": "2026-07-19",
  "qualificationVersionId": "OCR-6993:Version 2.0",
  "sourceSha256": "d682352b907c422bd5d994153bd5440b3146913e92e9a7524148515109f8cb3f",
  "extractionSha256": "2ef086dac6dbc9bd861b8f823c87f0cea188d8e4f8751d44de3fc3908dfac689",
  "paperCatalogSha256": "dd4e6d9adf47663aaba00e5ed96c073238ffadd1f068b3a2281e44b61d34d058",
  "declaredPapers": [
    "01"
  ],
  "assignments": [
    {
      "statementId": "OCR-6993-CODEX-p9-r3-b0-1",
      "statementType": "exam-rule",
      "applicability": {
        "kind": "not-specified"
      },
      "rationale": "Non-content records are retained for source accounting but do not map to assessment Papers.",
      "sourceReferences": [],
      "reviewStatus": "codex-reviewed"
    },
    {
      "statementId": "OCR-6993-CODEX-p9-r3-b1-1",
      "statementType": "exam-rule",
      "applicability": {
        "kind": "not-specified"
      },
      "rationale": "Non-content records are retained for source accounting but do not map to assessment Papers.",
      "sourceReferences": [],
      "reviewStatus": "codex-reviewed"
    },
    {
      "statementId": "OCR-6993-CODEX-p9-r3-b3-1",
      "statementType": "exam-rule",
      "applicability": {
        "kind": "not-specified"
      },
      "rationale": "Non-content records are retained for source accounting but do not map to assessment Papers.",
      "sourceReferences": [],
      "reviewStatus": "codex-reviewed"
    },
    {
      "statementId": "OCR-6993-CODEX-p9-r3-b4-1",
      "statementType": "exam-rule",
      "applicability": {
        "kind": "not-specified"
      },
      "rationale": "Non-content records are retained for source accounting but do not map to assessment Papers.",
      "sourceReferences": [],
      "reviewStatus": "codex-reviewed"
    },
    {
      "statementId": "OCR-6993-CODEX-p9-r3-b5-1",
      "statementType": "exam-rule",
      "applicability": {
        "kind": "not-specified"
      },
      "rationale": "Non-content records are retained for source accounting but do not map to assessment Papers.",
      "sourceReferences": [],
      "reviewStatus": "codex-reviewed"
    },
    {
      "statementId": "OCR-6993-CODEX-p10-r5-b0-1",
      "statementType": "teaching-note",
      "applicability": {
        "kind": "not-specified"
      },
      "rationale": "Non-content records are retained for source accounting but do not map to assessment Papers.",
      "sourceReferences": [],
      "reviewStatus": "codex-reviewed"
    },
    {
      "statementId": "OCR-6993-OFFICIAL-OCR-6993-AL1",
      "statementType": "assessable-content",
      "applicability": {
        "kind": "eligible",
        "papers": [
          "01"
        ]
      },
      "rationale": "Codex verified the statement tier against the official Paper tiers and the official assessment rule that the applicable syllabus content may be assessed on every Paper within that tier.",
      "sourceReferences": [
        {
          "sourceSha256": "d682352b907c422bd5d994153bd5440b3146913e92e9a7524148515109f8cb3f",
          "sourceUrl": "https://www.ocr.org.uk/Images/457916-specification-from-2018-.pdf",
          "locator": "page 8, page 23",
          "evidenceSummary": "Page 8 assessment overview: Paper 1 (01) is a 2-hour written paper with 100 marks, covering all syllabus content. Page 23 entry code table confirms component code 01 for Paper 1."
        }
      ],
      "reviewStatus": "codex-reviewed"
    },
    {
      "statementId": "OCR-6993-OFFICIAL-OCR-6993-AL10",
      "statementType": "assessable-content",
      "applicability": {
        "kind": "eligible",
        "papers": [
          "01"
        ]
      },
      "rationale": "Codex verified the statement tier against the official Paper tiers and the official assessment rule that the applicable syllabus content may be assessed on every Paper within that tier.",
      "sourceReferences": [
        {
          "sourceSha256": "d682352b907c422bd5d994153bd5440b3146913e92e9a7524148515109f8cb3f",
          "sourceUrl": "https://www.ocr.org.uk/Images/457916-specification-from-2018-.pdf",
          "locator": "page 8, page 23",
          "evidenceSummary": "Page 8 assessment overview: Paper 1 (01) is a 2-hour written paper with 100 marks, covering all syllabus content. Page 23 entry code table confirms component code 01 for Paper 1."
        }
      ],
      "reviewStatus": "codex-reviewed"
    },
    {
      "statementId": "OCR-6993-OFFICIAL-OCR-6993-AL11",
      "statementType": "assessable-content",
      "applicability": {
        "kind": "eligible",
        "papers": [
          "01"
        ]
      },
      "rationale": "Codex verified the statement tier against the official Paper tiers and the official assessment rule that the applicable syllabus content may be assessed on every Paper within that tier.",
      "sourceReferences": [
        {
          "sourceSha256": "d682352b907c422bd5d994153bd5440b3146913e92e9a7524148515109f8cb3f",
          "sourceUrl": "https://www.ocr.org.uk/Images/457916-specification-from-2018-.pdf",
          "locator": "page 8, page 23",
          "evidenceSummary": "Page 8 assessment overview: Paper 1 (01) is a 2-hour written paper with 100 marks, covering all syllabus content. Page 23 entry code table confirms component code 01 for Paper 1."
        }
      ],
      "reviewStatus": "codex-reviewed"
    },
    {
      "statementId": "OCR-6993-OFFICIAL-OCR-6993-AL2",
      "statementType": "assessable-content",
      "applicability": {
        "kind": "eligible",
        "papers": [
          "01"
        ]
      },
      "rationale": "Codex verified the statement tier against the official Paper tiers and the official assessment rule that the applicable syllabus content may be assessed on every Paper within that tier.",
      "sourceReferences": [
        {
          "sourceSha256": "d682352b907c422bd5d994153bd5440b3146913e92e9a7524148515109f8cb3f",
          "sourceUrl": "https://www.ocr.org.uk/Images/457916-specification-from-2018-.pdf",
          "locator": "page 8, page 23",
          "evidenceSummary": "Page 8 assessment overview: Paper 1 (01) is a 2-hour written paper with 100 marks, covering all syllabus content. Page 23 entry code table confirms component code 01 for Paper 1."
        }
      ],
      "reviewStatus": "codex-reviewed"
    },
    {
      "statementId": "OCR-6993-OFFICIAL-OCR-6993-AL3",
      "statementType": "assessable-content",
      "applicability": {
        "kind": "eligible",
        "papers": [
          "01"
        ]
      },
      "rationale": "Codex verified the statement tier against the official Paper tiers and the official assessment rule that the applicable syllabus content may be assessed on every Paper within that tier.",
      "sourceReferences": [
        {
          "sourceSha256": "d682352b907c422bd5d994153bd5440b3146913e92e9a7524148515109f8cb3f",
          "sourceUrl": "https://www.ocr.org.uk/Images/457916-specification-from-2018-.pdf",
          "locator": "page 8, page 23",
          "evidenceSummary": "Page 8 assessment overview: Paper 1 (01) is a 2-hour written paper with 100 marks, covering all syllabus content. Page 23 entry code table confirms component code 01 for Paper 1."
        }
      ],
      "reviewStatus": "codex-reviewed"
    },
    {
      "statementId": "OCR-6993-OFFICIAL-OCR-6993-AL4",
      "statementType": "assessable-content",
      "applicability": {
        "kind": "eligible",
        "papers": [
          "01"
        ]
      },
      "rationale": "Codex verified the statement tier against the official Paper tiers and the official assessment rule that the applicable syllabus content may be assessed on every Paper within that tier.",
      "sourceReferences": [
        {
          "sourceSha256": "d682352b907c422bd5d994153bd5440b3146913e92e9a7524148515109f8cb3f",
          "sourceUrl": "https://www.ocr.org.uk/Images/457916-specification-from-2018-.pdf",
          "locator": "page 8, page 23",
          "evidenceSummary": "Page 8 assessment overview: Paper 1 (01) is a 2-hour written paper with 100 marks, covering all syllabus content. Page 23 entry code table confirms component code 01 for Paper 1."
        }
      ],
      "reviewStatus": "codex-reviewed"
    },
    {
      "statementId": "OCR-6993-OFFICIAL-OCR-6993-AL5",
      "statementType": "assessable-content",
      "applicability": {
        "kind": "eligible",
        "papers": [
          "01"
        ]
      },
      "rationale": "Codex verified the statement tier against the official Paper tiers and the official assessment rule that the applicable syllabus content may be assessed on every Paper within that tier.",
      "sourceReferences": [
        {
          "sourceSha256": "d682352b907c422bd5d994153bd5440b3146913e92e9a7524148515109f8cb3f",
          "sourceUrl": "https://www.ocr.org.uk/Images/457916-specification-from-2018-.pdf",
          "locator": "page 8, page 23",
          "evidenceSummary": "Page 8 assessment overview: Paper 1 (01) is a 2-hour written paper with 100 marks, covering all syllabus content. Page 23 entry code table confirms component code 01 for Paper 1."
        }
      ],
      "reviewStatus": "codex-reviewed"
    },
    {
      "statementId": "OCR-6993-OFFICIAL-OCR-6993-AL6",
      "statementType": "assessable-content",
      "applicability": {
        "kind": "eligible",
        "papers": [
          "01"
        ]
      },
      "rationale": "Codex verified the statement tier against the official Paper tiers and the official assessment rule that the applicable syllabus content may be assessed on every Paper within that tier.",
      "sourceReferences": [
        {
          "sourceSha256": "d682352b907c422bd5d994153bd5440b3146913e92e9a7524148515109f8cb3f",
          "sourceUrl": "https://www.ocr.org.uk/Images/457916-specification-from-2018-.pdf",
          "locator": "page 8, page 23",
          "evidenceSummary": "Page 8 assessment overview: Paper 1 (01) is a 2-hour written paper with 100 marks, covering all syllabus content. Page 23 entry code table confirms component code 01 for Paper 1."
        }
      ],
      "reviewStatus": "codex-reviewed"
    },
    {
      "statementId": "OCR-6993-OFFICIAL-OCR-6993-AL7",
      "statementType": "assessable-content",
      "applicability": {
        "kind": "eligible",
        "papers": [
          "01"
        ]
      },
      "rationale": "Codex verified the statement tier against the official Paper tiers and the official assessment rule that the applicable syllabus content may be assessed on every Paper within that tier.",
      "sourceReferences": [
        {
          "sourceSha256": "d682352b907c422bd5d994153bd5440b3146913e92e9a7524148515109f8cb3f",
          "sourceUrl": "https://www.ocr.org.uk/Images/457916-specification-from-2018-.pdf",
          "locator": "page 8, page 23",
          "evidenceSummary": "Page 8 assessment overview: Paper 1 (01) is a 2-hour written paper with 100 marks, covering all syllabus content. Page 23 entry code table confirms component code 01 for Paper 1."
        }
      ],
      "reviewStatus": "codex-reviewed"
    },
    {
      "statementId": "OCR-6993-OFFICIAL-OCR-6993-AL8",
      "statementType": "assessable-content",
      "applicability": {
        "kind": "eligible",
        "papers": [
          "01"
        ]
      },
      "rationale": "Codex verified the statement tier against the official Paper tiers and the official assessment rule that the applicable syllabus content may be assessed on every Paper within that tier.",
      "sourceReferences": [
        {
          "sourceSha256": "d682352b907c422bd5d994153bd5440b3146913e92e9a7524148515109f8cb3f",
          "sourceUrl": "https://www.ocr.org.uk/Images/457916-specification-from-2018-.pdf",
          "locator": "page 8, page 23",
          "evidenceSummary": "Page 8 assessment overview: Paper 1 (01) is a 2-hour written paper with 100 marks, covering all syllabus content. Page 23 entry code table confirms component code 01 for Paper 1."
        }
      ],
      "reviewStatus": "codex-reviewed"
    },
    {
      "statementId": "OCR-6993-OFFICIAL-OCR-6993-AL9",
      "statementType": "assessable-content",
      "applicability": {
        "kind": "eligible",
        "papers": [
          "01"
        ]
      },
      "rationale": "Codex verified the statement tier against the official Paper tiers and the official assessment rule that the applicable syllabus content may be assessed on every Paper within that tier.",
      "sourceReferences": [
        {
          "sourceSha256": "d682352b907c422bd5d994153bd5440b3146913e92e9a7524148515109f8cb3f",
          "sourceUrl": "https://www.ocr.org.uk/Images/457916-specification-from-2018-.pdf",
          "locator": "page 8, page 23",
          "evidenceSummary": "Page 8 assessment overview: Paper 1 (01) is a 2-hour written paper with 100 marks, covering all syllabus content. Page 23 entry code table confirms component code 01 for Paper 1."
        }
      ],
      "reviewStatus": "codex-reviewed"
    },
    {
      "statementId": "OCR-6993-OFFICIAL-OCR-6993-EN1",
      "statementType": "assessable-content",
      "applicability": {
        "kind": "eligible",
        "papers": [
          "01"
        ]
      },
      "rationale": "Codex verified the statement tier against the official Paper tiers and the official assessment rule that the applicable syllabus content may be assessed on every Paper within that tier.",
      "sourceReferences": [
        {
          "sourceSha256": "d682352b907c422bd5d994153bd5440b3146913e92e9a7524148515109f8cb3f",
          "sourceUrl": "https://www.ocr.org.uk/Images/457916-specification-from-2018-.pdf",
          "locator": "page 8, page 23",
          "evidenceSummary": "Page 8 assessment overview: Paper 1 (01) is a 2-hour written paper with 100 marks, covering all syllabus content. Page 23 entry code table confirms component code 01 for Paper 1."
        }
      ],
      "reviewStatus": "codex-reviewed"
    },
    {
      "statementId": "OCR-6993-OFFICIAL-OCR-6993-EN2",
      "statementType": "assessable-content",
      "applicability": {
        "kind": "eligible",
        "papers": [
          "01"
        ]
      },
      "rationale": "Codex verified the statement tier against the official Paper tiers and the official assessment rule that the applicable syllabus content may be assessed on every Paper within that tier.",
      "sourceReferences": [
        {
          "sourceSha256": "d682352b907c422bd5d994153bd5440b3146913e92e9a7524148515109f8cb3f",
          "sourceUrl": "https://www.ocr.org.uk/Images/457916-specification-from-2018-.pdf",
          "locator": "page 8, page 23",
          "evidenceSummary": "Page 8 assessment overview: Paper 1 (01) is a 2-hour written paper with 100 marks, covering all syllabus content. Page 23 entry code table confirms component code 01 for Paper 1."
        }
      ],
      "reviewStatus": "codex-reviewed"
    },
    {
      "statementId": "OCR-6993-OFFICIAL-OCR-6993-EN3",
      "statementType": "assessable-content",
      "applicability": {
        "kind": "eligible",
        "papers": [
          "01"
        ]
      },
      "rationale": "Codex verified the statement tier against the official Paper tiers and the official assessment rule that the applicable syllabus content may be assessed on every Paper within that tier.",
      "sourceReferences": [
        {
          "sourceSha256": "d682352b907c422bd5d994153bd5440b3146913e92e9a7524148515109f8cb3f",
          "sourceUrl": "https://www.ocr.org.uk/Images/457916-specification-from-2018-.pdf",
          "locator": "page 8, page 23",
          "evidenceSummary": "Page 8 assessment overview: Paper 1 (01) is a 2-hour written paper with 100 marks, covering all syllabus content. Page 23 entry code table confirms component code 01 for Paper 1."
        }
      ],
      "reviewStatus": "codex-reviewed"
    },
    {
      "statementId": "OCR-6993-OFFICIAL-OCR-6993-EN4",
      "statementType": "assessable-content",
      "applicability": {
        "kind": "eligible",
        "papers": [
          "01"
        ]
      },
      "rationale": "Codex verified the statement tier against the official Paper tiers and the official assessment rule that the applicable syllabus content may be assessed on every Paper within that tier.",
      "sourceReferences": [
        {
          "sourceSha256": "d682352b907c422bd5d994153bd5440b3146913e92e9a7524148515109f8cb3f",
          "sourceUrl": "https://www.ocr.org.uk/Images/457916-specification-from-2018-.pdf",
          "locator": "page 8, page 23",
          "evidenceSummary": "Page 8 assessment overview: Paper 1 (01) is a 2-hour written paper with 100 marks, covering all syllabus content. Page 23 entry code table confirms component code 01 for Paper 1."
        }
      ],
      "reviewStatus": "codex-reviewed"
    },
    {
      "statementId": "OCR-6993-OFFICIAL-OCR-6993-EN5",
      "statementType": "assessable-content",
      "applicability": {
        "kind": "eligible",
        "papers": [
          "01"
        ]
      },
      "rationale": "Codex verified the statement tier against the official Paper tiers and the official assessment rule that the applicable syllabus content may be assessed on every Paper within that tier.",
      "sourceReferences": [
        {
          "sourceSha256": "d682352b907c422bd5d994153bd5440b3146913e92e9a7524148515109f8cb3f",
          "sourceUrl": "https://www.ocr.org.uk/Images/457916-specification-from-2018-.pdf",
          "locator": "page 8, page 23",
          "evidenceSummary": "Page 8 assessment overview: Paper 1 (01) is a 2-hour written paper with 100 marks, covering all syllabus content. Page 23 entry code table confirms component code 01 for Paper 1."
        }
      ],
      "reviewStatus": "codex-reviewed"
    },
    {
      "statementId": "OCR-6993-OFFICIAL-OCR-6993-EN6",
      "statementType": "assessable-content",
      "applicability": {
        "kind": "eligible",
        "papers": [
          "01"
        ]
      },
      "rationale": "Codex verified the statement tier against the official Paper tiers and the official assessment rule that the applicable syllabus content may be assessed on every Paper within that tier.",
      "sourceReferences": [
        {
          "sourceSha256": "d682352b907c422bd5d994153bd5440b3146913e92e9a7524148515109f8cb3f",
          "sourceUrl": "https://www.ocr.org.uk/Images/457916-specification-from-2018-.pdf",
          "locator": "page 8, page 23",
          "evidenceSummary": "Page 8 assessment overview: Paper 1 (01) is a 2-hour written paper with 100 marks, covering all syllabus content. Page 23 entry code table confirms component code 01 for Paper 1."
        }
      ],
      "reviewStatus": "codex-reviewed"
    },
    {
      "statementId": "OCR-6993-OFFICIAL-OCR-6993-CG1",
      "statementType": "assessable-content",
      "applicability": {
        "kind": "eligible",
        "papers": [
          "01"
        ]
      },
      "rationale": "Codex verified the statement tier against the official Paper tiers and the official assessment rule that the applicable syllabus content may be assessed on every Paper within that tier.",
      "sourceReferences": [
        {
          "sourceSha256": "d682352b907c422bd5d994153bd5440b3146913e92e9a7524148515109f8cb3f",
          "sourceUrl": "https://www.ocr.org.uk/Images/457916-specification-from-2018-.pdf",
          "locator": "page 8, page 23",
          "evidenceSummary": "Page 8 assessment overview: Paper 1 (01) is a 2-hour written paper with 100 marks, covering all syllabus content. Page 23 entry code table confirms component code 01 for Paper 1."
        }
      ],
      "reviewStatus": "codex-reviewed"
    },
    {
      "statementId": "OCR-6993-OFFICIAL-OCR-6993-CG2",
      "statementType": "assessable-content",
      "applicability": {
        "kind": "eligible",
        "papers": [
          "01"
        ]
      },
      "rationale": "Codex verified the statement tier against the official Paper tiers and the official assessment rule that the applicable syllabus content may be assessed on every Paper within that tier.",
      "sourceReferences": [
        {
          "sourceSha256": "d682352b907c422bd5d994153bd5440b3146913e92e9a7524148515109f8cb3f",
          "sourceUrl": "https://www.ocr.org.uk/Images/457916-specification-from-2018-.pdf",
          "locator": "page 8, page 23",
          "evidenceSummary": "Page 8 assessment overview: Paper 1 (01) is a 2-hour written paper with 100 marks, covering all syllabus content. Page 23 entry code table confirms component code 01 for Paper 1."
        }
      ],
      "reviewStatus": "codex-reviewed"
    },
    {
      "statementId": "OCR-6993-OFFICIAL-OCR-6993-CG3",
      "statementType": "assessable-content",
      "applicability": {
        "kind": "eligible",
        "papers": [
          "01"
        ]
      },
      "rationale": "Codex verified the statement tier against the official Paper tiers and the official assessment rule that the applicable syllabus content may be assessed on every Paper within that tier.",
      "sourceReferences": [
        {
          "sourceSha256": "d682352b907c422bd5d994153bd5440b3146913e92e9a7524148515109f8cb3f",
          "sourceUrl": "https://www.ocr.org.uk/Images/457916-specification-from-2018-.pdf",
          "locator": "page 8, page 23",
          "evidenceSummary": "Page 8 assessment overview: Paper 1 (01) is a 2-hour written paper with 100 marks, covering all syllabus content. Page 23 entry code table confirms component code 01 for Paper 1."
        }
      ],
      "reviewStatus": "codex-reviewed"
    },
    {
      "statementId": "OCR-6993-OFFICIAL-OCR-6993-CG4",
      "statementType": "assessable-content",
      "applicability": {
        "kind": "eligible",
        "papers": [
          "01"
        ]
      },
      "rationale": "Codex verified the statement tier against the official Paper tiers and the official assessment rule that the applicable syllabus content may be assessed on every Paper within that tier.",
      "sourceReferences": [
        {
          "sourceSha256": "d682352b907c422bd5d994153bd5440b3146913e92e9a7524148515109f8cb3f",
          "sourceUrl": "https://www.ocr.org.uk/Images/457916-specification-from-2018-.pdf",
          "locator": "page 8, page 23",
          "evidenceSummary": "Page 8 assessment overview: Paper 1 (01) is a 2-hour written paper with 100 marks, covering all syllabus content. Page 23 entry code table confirms component code 01 for Paper 1."
        }
      ],
      "reviewStatus": "codex-reviewed"
    },
    {
      "statementId": "OCR-6993-OFFICIAL-OCR-6993-CG5",
      "statementType": "assessable-content",
      "applicability": {
        "kind": "eligible",
        "papers": [
          "01"
        ]
      },
      "rationale": "Codex verified the statement tier against the official Paper tiers and the official assessment rule that the applicable syllabus content may be assessed on every Paper within that tier.",
      "sourceReferences": [
        {
          "sourceSha256": "d682352b907c422bd5d994153bd5440b3146913e92e9a7524148515109f8cb3f",
          "sourceUrl": "https://www.ocr.org.uk/Images/457916-specification-from-2018-.pdf",
          "locator": "page 8, page 23",
          "evidenceSummary": "Page 8 assessment overview: Paper 1 (01) is a 2-hour written paper with 100 marks, covering all syllabus content. Page 23 entry code table confirms component code 01 for Paper 1."
        }
      ],
      "reviewStatus": "codex-reviewed"
    },
    {
      "statementId": "OCR-6993-OFFICIAL-OCR-6993-CG6",
      "statementType": "assessable-content",
      "applicability": {
        "kind": "eligible",
        "papers": [
          "01"
        ]
      },
      "rationale": "Codex verified the statement tier against the official Paper tiers and the official assessment rule that the applicable syllabus content may be assessed on every Paper within that tier.",
      "sourceReferences": [
        {
          "sourceSha256": "d682352b907c422bd5d994153bd5440b3146913e92e9a7524148515109f8cb3f",
          "sourceUrl": "https://www.ocr.org.uk/Images/457916-specification-from-2018-.pdf",
          "locator": "page 8, page 23",
          "evidenceSummary": "Page 8 assessment overview: Paper 1 (01) is a 2-hour written paper with 100 marks, covering all syllabus content. Page 23 entry code table confirms component code 01 for Paper 1."
        }
      ],
      "reviewStatus": "codex-reviewed"
    },
    {
      "statementId": "OCR-6993-OFFICIAL-OCR-6993-CG7",
      "statementType": "assessable-content",
      "applicability": {
        "kind": "eligible",
        "papers": [
          "01"
        ]
      },
      "rationale": "Codex verified the statement tier against the official Paper tiers and the official assessment rule that the applicable syllabus content may be assessed on every Paper within that tier.",
      "sourceReferences": [
        {
          "sourceSha256": "d682352b907c422bd5d994153bd5440b3146913e92e9a7524148515109f8cb3f",
          "sourceUrl": "https://www.ocr.org.uk/Images/457916-specification-from-2018-.pdf",
          "locator": "page 8, page 23",
          "evidenceSummary": "Page 8 assessment overview: Paper 1 (01) is a 2-hour written paper with 100 marks, covering all syllabus content. Page 23 entry code table confirms component code 01 for Paper 1."
        }
      ],
      "reviewStatus": "codex-reviewed"
    },
    {
      "statementId": "OCR-6993-OFFICIAL-OCR-6993-CG8",
      "statementType": "assessable-content",
      "applicability": {
        "kind": "eligible",
        "papers": [
          "01"
        ]
      },
      "rationale": "Codex verified the statement tier against the official Paper tiers and the official assessment rule that the applicable syllabus content may be assessed on every Paper within that tier.",
      "sourceReferences": [
        {
          "sourceSha256": "d682352b907c422bd5d994153bd5440b3146913e92e9a7524148515109f8cb3f",
          "sourceUrl": "https://www.ocr.org.uk/Images/457916-specification-from-2018-.pdf",
          "locator": "page 8, page 23",
          "evidenceSummary": "Page 8 assessment overview: Paper 1 (01) is a 2-hour written paper with 100 marks, covering all syllabus content. Page 23 entry code table confirms component code 01 for Paper 1."
        }
      ],
      "reviewStatus": "codex-reviewed"
    },
    {
      "statementId": "OCR-6993-OFFICIAL-OCR-6993-PT1",
      "statementType": "assessable-content",
      "applicability": {
        "kind": "eligible",
        "papers": [
          "01"
        ]
      },
      "rationale": "Codex verified the statement tier against the official Paper tiers and the official assessment rule that the applicable syllabus content may be assessed on every Paper within that tier.",
      "sourceReferences": [
        {
          "sourceSha256": "d682352b907c422bd5d994153bd5440b3146913e92e9a7524148515109f8cb3f",
          "sourceUrl": "https://www.ocr.org.uk/Images/457916-specification-from-2018-.pdf",
          "locator": "page 8, page 23",
          "evidenceSummary": "Page 8 assessment overview: Paper 1 (01) is a 2-hour written paper with 100 marks, covering all syllabus content. Page 23 entry code table confirms component code 01 for Paper 1."
        }
      ],
      "reviewStatus": "codex-reviewed"
    },
    {
      "statementId": "OCR-6993-OFFICIAL-OCR-6993-PT2",
      "statementType": "assessable-content",
      "applicability": {
        "kind": "eligible",
        "papers": [
          "01"
        ]
      },
      "rationale": "Codex verified the statement tier against the official Paper tiers and the official assessment rule that the applicable syllabus content may be assessed on every Paper within that tier.",
      "sourceReferences": [
        {
          "sourceSha256": "d682352b907c422bd5d994153bd5440b3146913e92e9a7524148515109f8cb3f",
          "sourceUrl": "https://www.ocr.org.uk/Images/457916-specification-from-2018-.pdf",
          "locator": "page 8, page 23",
          "evidenceSummary": "Page 8 assessment overview: Paper 1 (01) is a 2-hour written paper with 100 marks, covering all syllabus content. Page 23 entry code table confirms component code 01 for Paper 1."
        }
      ],
      "reviewStatus": "codex-reviewed"
    },
    {
      "statementId": "OCR-6993-OFFICIAL-OCR-6993-PT3",
      "statementType": "assessable-content",
      "applicability": {
        "kind": "eligible",
        "papers": [
          "01"
        ]
      },
      "rationale": "Codex verified the statement tier against the official Paper tiers and the official assessment rule that the applicable syllabus content may be assessed on every Paper within that tier.",
      "sourceReferences": [
        {
          "sourceSha256": "d682352b907c422bd5d994153bd5440b3146913e92e9a7524148515109f8cb3f",
          "sourceUrl": "https://www.ocr.org.uk/Images/457916-specification-from-2018-.pdf",
          "locator": "page 8, page 23",
          "evidenceSummary": "Page 8 assessment overview: Paper 1 (01) is a 2-hour written paper with 100 marks, covering all syllabus content. Page 23 entry code table confirms component code 01 for Paper 1."
        }
      ],
      "reviewStatus": "codex-reviewed"
    },
    {
      "statementId": "OCR-6993-OFFICIAL-OCR-6993-PT4",
      "statementType": "assessable-content",
      "applicability": {
        "kind": "eligible",
        "papers": [
          "01"
        ]
      },
      "rationale": "Codex verified the statement tier against the official Paper tiers and the official assessment rule that the applicable syllabus content may be assessed on every Paper within that tier.",
      "sourceReferences": [
        {
          "sourceSha256": "d682352b907c422bd5d994153bd5440b3146913e92e9a7524148515109f8cb3f",
          "sourceUrl": "https://www.ocr.org.uk/Images/457916-specification-from-2018-.pdf",
          "locator": "page 8, page 23",
          "evidenceSummary": "Page 8 assessment overview: Paper 1 (01) is a 2-hour written paper with 100 marks, covering all syllabus content. Page 23 entry code table confirms component code 01 for Paper 1."
        }
      ],
      "reviewStatus": "codex-reviewed"
    },
    {
      "statementId": "OCR-6993-OFFICIAL-OCR-6993-PT5",
      "statementType": "assessable-content",
      "applicability": {
        "kind": "eligible",
        "papers": [
          "01"
        ]
      },
      "rationale": "Codex verified the statement tier against the official Paper tiers and the official assessment rule that the applicable syllabus content may be assessed on every Paper within that tier.",
      "sourceReferences": [
        {
          "sourceSha256": "d682352b907c422bd5d994153bd5440b3146913e92e9a7524148515109f8cb3f",
          "sourceUrl": "https://www.ocr.org.uk/Images/457916-specification-from-2018-.pdf",
          "locator": "page 8, page 23",
          "evidenceSummary": "Page 8 assessment overview: Paper 1 (01) is a 2-hour written paper with 100 marks, covering all syllabus content. Page 23 entry code table confirms component code 01 for Paper 1."
        }
      ],
      "reviewStatus": "codex-reviewed"
    },
    {
      "statementId": "OCR-6993-OFFICIAL-OCR-6993-PT6",
      "statementType": "assessable-content",
      "applicability": {
        "kind": "eligible",
        "papers": [
          "01"
        ]
      },
      "rationale": "Codex verified the statement tier against the official Paper tiers and the official assessment rule that the applicable syllabus content may be assessed on every Paper within that tier.",
      "sourceReferences": [
        {
          "sourceSha256": "d682352b907c422bd5d994153bd5440b3146913e92e9a7524148515109f8cb3f",
          "sourceUrl": "https://www.ocr.org.uk/Images/457916-specification-from-2018-.pdf",
          "locator": "page 8, page 23",
          "evidenceSummary": "Page 8 assessment overview: Paper 1 (01) is a 2-hour written paper with 100 marks, covering all syllabus content. Page 23 entry code table confirms component code 01 for Paper 1."
        }
      ],
      "reviewStatus": "codex-reviewed"
    },
    {
      "statementId": "OCR-6993-OFFICIAL-OCR-6993-CA1",
      "statementType": "assessable-content",
      "applicability": {
        "kind": "eligible",
        "papers": [
          "01"
        ]
      },
      "rationale": "Codex verified the statement tier against the official Paper tiers and the official assessment rule that the applicable syllabus content may be assessed on every Paper within that tier.",
      "sourceReferences": [
        {
          "sourceSha256": "d682352b907c422bd5d994153bd5440b3146913e92e9a7524148515109f8cb3f",
          "sourceUrl": "https://www.ocr.org.uk/Images/457916-specification-from-2018-.pdf",
          "locator": "page 8, page 23",
          "evidenceSummary": "Page 8 assessment overview: Paper 1 (01) is a 2-hour written paper with 100 marks, covering all syllabus content. Page 23 entry code table confirms component code 01 for Paper 1."
        }
      ],
      "reviewStatus": "codex-reviewed"
    },
    {
      "statementId": "OCR-6993-OFFICIAL-OCR-6993-CA10",
      "statementType": "assessable-content",
      "applicability": {
        "kind": "eligible",
        "papers": [
          "01"
        ]
      },
      "rationale": "Codex verified the statement tier against the official Paper tiers and the official assessment rule that the applicable syllabus content may be assessed on every Paper within that tier.",
      "sourceReferences": [
        {
          "sourceSha256": "d682352b907c422bd5d994153bd5440b3146913e92e9a7524148515109f8cb3f",
          "sourceUrl": "https://www.ocr.org.uk/Images/457916-specification-from-2018-.pdf",
          "locator": "page 8, page 23",
          "evidenceSummary": "Page 8 assessment overview: Paper 1 (01) is a 2-hour written paper with 100 marks, covering all syllabus content. Page 23 entry code table confirms component code 01 for Paper 1."
        }
      ],
      "reviewStatus": "codex-reviewed"
    },
    {
      "statementId": "OCR-6993-OFFICIAL-OCR-6993-CA11",
      "statementType": "assessable-content",
      "applicability": {
        "kind": "eligible",
        "papers": [
          "01"
        ]
      },
      "rationale": "Codex verified the statement tier against the official Paper tiers and the official assessment rule that the applicable syllabus content may be assessed on every Paper within that tier.",
      "sourceReferences": [
        {
          "sourceSha256": "d682352b907c422bd5d994153bd5440b3146913e92e9a7524148515109f8cb3f",
          "sourceUrl": "https://www.ocr.org.uk/Images/457916-specification-from-2018-.pdf",
          "locator": "page 8, page 23",
          "evidenceSummary": "Page 8 assessment overview: Paper 1 (01) is a 2-hour written paper with 100 marks, covering all syllabus content. Page 23 entry code table confirms component code 01 for Paper 1."
        }
      ],
      "reviewStatus": "codex-reviewed"
    },
    {
      "statementId": "OCR-6993-OFFICIAL-OCR-6993-CA12",
      "statementType": "assessable-content",
      "applicability": {
        "kind": "eligible",
        "papers": [
          "01"
        ]
      },
      "rationale": "Codex verified the statement tier against the official Paper tiers and the official assessment rule that the applicable syllabus content may be assessed on every Paper within that tier.",
      "sourceReferences": [
        {
          "sourceSha256": "d682352b907c422bd5d994153bd5440b3146913e92e9a7524148515109f8cb3f",
          "sourceUrl": "https://www.ocr.org.uk/Images/457916-specification-from-2018-.pdf",
          "locator": "page 8, page 23",
          "evidenceSummary": "Page 8 assessment overview: Paper 1 (01) is a 2-hour written paper with 100 marks, covering all syllabus content. Page 23 entry code table confirms component code 01 for Paper 1."
        }
      ],
      "reviewStatus": "codex-reviewed"
    },
    {
      "statementId": "OCR-6993-OFFICIAL-OCR-6993-CA13",
      "statementType": "assessable-content",
      "applicability": {
        "kind": "eligible",
        "papers": [
          "01"
        ]
      },
      "rationale": "Codex verified the statement tier against the official Paper tiers and the official assessment rule that the applicable syllabus content may be assessed on every Paper within that tier.",
      "sourceReferences": [
        {
          "sourceSha256": "d682352b907c422bd5d994153bd5440b3146913e92e9a7524148515109f8cb3f",
          "sourceUrl": "https://www.ocr.org.uk/Images/457916-specification-from-2018-.pdf",
          "locator": "page 8, page 23",
          "evidenceSummary": "Page 8 assessment overview: Paper 1 (01) is a 2-hour written paper with 100 marks, covering all syllabus content. Page 23 entry code table confirms component code 01 for Paper 1."
        }
      ],
      "reviewStatus": "codex-reviewed"
    },
    {
      "statementId": "OCR-6993-OFFICIAL-OCR-6993-CA14",
      "statementType": "assessable-content",
      "applicability": {
        "kind": "eligible",
        "papers": [
          "01"
        ]
      },
      "rationale": "Codex verified the statement tier against the official Paper tiers and the official assessment rule that the applicable syllabus content may be assessed on every Paper within that tier.",
      "sourceReferences": [
        {
          "sourceSha256": "d682352b907c422bd5d994153bd5440b3146913e92e9a7524148515109f8cb3f",
          "sourceUrl": "https://www.ocr.org.uk/Images/457916-specification-from-2018-.pdf",
          "locator": "page 8, page 23",
          "evidenceSummary": "Page 8 assessment overview: Paper 1 (01) is a 2-hour written paper with 100 marks, covering all syllabus content. Page 23 entry code table confirms component code 01 for Paper 1."
        }
      ],
      "reviewStatus": "codex-reviewed"
    },
    {
      "statementId": "OCR-6993-OFFICIAL-OCR-6993-CA15",
      "statementType": "assessable-content",
      "applicability": {
        "kind": "eligible",
        "papers": [
          "01"
        ]
      },
      "rationale": "Codex verified the statement tier against the official Paper tiers and the official assessment rule that the applicable syllabus content may be assessed on every Paper within that tier.",
      "sourceReferences": [
        {
          "sourceSha256": "d682352b907c422bd5d994153bd5440b3146913e92e9a7524148515109f8cb3f",
          "sourceUrl": "https://www.ocr.org.uk/Images/457916-specification-from-2018-.pdf",
          "locator": "page 8, page 23",
          "evidenceSummary": "Page 8 assessment overview: Paper 1 (01) is a 2-hour written paper with 100 marks, covering all syllabus content. Page 23 entry code table confirms component code 01 for Paper 1."
        }
      ],
      "reviewStatus": "codex-reviewed"
    },
    {
      "statementId": "OCR-6993-OFFICIAL-OCR-6993-CA2",
      "statementType": "assessable-content",
      "applicability": {
        "kind": "eligible",
        "papers": [
          "01"
        ]
      },
      "rationale": "Codex verified the statement tier against the official Paper tiers and the official assessment rule that the applicable syllabus content may be assessed on every Paper within that tier.",
      "sourceReferences": [
        {
          "sourceSha256": "d682352b907c422bd5d994153bd5440b3146913e92e9a7524148515109f8cb3f",
          "sourceUrl": "https://www.ocr.org.uk/Images/457916-specification-from-2018-.pdf",
          "locator": "page 8, page 23",
          "evidenceSummary": "Page 8 assessment overview: Paper 1 (01) is a 2-hour written paper with 100 marks, covering all syllabus content. Page 23 entry code table confirms component code 01 for Paper 1."
        }
      ],
      "reviewStatus": "codex-reviewed"
    },
    {
      "statementId": "OCR-6993-OFFICIAL-OCR-6993-CA3",
      "statementType": "assessable-content",
      "applicability": {
        "kind": "eligible",
        "papers": [
          "01"
        ]
      },
      "rationale": "Codex verified the statement tier against the official Paper tiers and the official assessment rule that the applicable syllabus content may be assessed on every Paper within that tier.",
      "sourceReferences": [
        {
          "sourceSha256": "d682352b907c422bd5d994153bd5440b3146913e92e9a7524148515109f8cb3f",
          "sourceUrl": "https://www.ocr.org.uk/Images/457916-specification-from-2018-.pdf",
          "locator": "page 8, page 23",
          "evidenceSummary": "Page 8 assessment overview: Paper 1 (01) is a 2-hour written paper with 100 marks, covering all syllabus content. Page 23 entry code table confirms component code 01 for Paper 1."
        }
      ],
      "reviewStatus": "codex-reviewed"
    },
    {
      "statementId": "OCR-6993-OFFICIAL-OCR-6993-CA4",
      "statementType": "assessable-content",
      "applicability": {
        "kind": "eligible",
        "papers": [
          "01"
        ]
      },
      "rationale": "Codex verified the statement tier against the official Paper tiers and the official assessment rule that the applicable syllabus content may be assessed on every Paper within that tier.",
      "sourceReferences": [
        {
          "sourceSha256": "d682352b907c422bd5d994153bd5440b3146913e92e9a7524148515109f8cb3f",
          "sourceUrl": "https://www.ocr.org.uk/Images/457916-specification-from-2018-.pdf",
          "locator": "page 8, page 23",
          "evidenceSummary": "Page 8 assessment overview: Paper 1 (01) is a 2-hour written paper with 100 marks, covering all syllabus content. Page 23 entry code table confirms component code 01 for Paper 1."
        }
      ],
      "reviewStatus": "codex-reviewed"
    },
    {
      "statementId": "OCR-6993-OFFICIAL-OCR-6993-CA5",
      "statementType": "assessable-content",
      "applicability": {
        "kind": "eligible",
        "papers": [
          "01"
        ]
      },
      "rationale": "Codex verified the statement tier against the official Paper tiers and the official assessment rule that the applicable syllabus content may be assessed on every Paper within that tier.",
      "sourceReferences": [
        {
          "sourceSha256": "d682352b907c422bd5d994153bd5440b3146913e92e9a7524148515109f8cb3f",
          "sourceUrl": "https://www.ocr.org.uk/Images/457916-specification-from-2018-.pdf",
          "locator": "page 8, page 23",
          "evidenceSummary": "Page 8 assessment overview: Paper 1 (01) is a 2-hour written paper with 100 marks, covering all syllabus content. Page 23 entry code table confirms component code 01 for Paper 1."
        }
      ],
      "reviewStatus": "codex-reviewed"
    },
    {
      "statementId": "OCR-6993-OFFICIAL-OCR-6993-CA6",
      "statementType": "assessable-content",
      "applicability": {
        "kind": "eligible",
        "papers": [
          "01"
        ]
      },
      "rationale": "Codex verified the statement tier against the official Paper tiers and the official assessment rule that the applicable syllabus content may be assessed on every Paper within that tier.",
      "sourceReferences": [
        {
          "sourceSha256": "d682352b907c422bd5d994153bd5440b3146913e92e9a7524148515109f8cb3f",
          "sourceUrl": "https://www.ocr.org.uk/Images/457916-specification-from-2018-.pdf",
          "locator": "page 8, page 23",
          "evidenceSummary": "Page 8 assessment overview: Paper 1 (01) is a 2-hour written paper with 100 marks, covering all syllabus content. Page 23 entry code table confirms component code 01 for Paper 1."
        }
      ],
      "reviewStatus": "codex-reviewed"
    },
    {
      "statementId": "OCR-6993-OFFICIAL-OCR-6993-CA7",
      "statementType": "assessable-content",
      "applicability": {
        "kind": "eligible",
        "papers": [
          "01"
        ]
      },
      "rationale": "Codex verified the statement tier against the official Paper tiers and the official assessment rule that the applicable syllabus content may be assessed on every Paper within that tier.",
      "sourceReferences": [
        {
          "sourceSha256": "d682352b907c422bd5d994153bd5440b3146913e92e9a7524148515109f8cb3f",
          "sourceUrl": "https://www.ocr.org.uk/Images/457916-specification-from-2018-.pdf",
          "locator": "page 8, page 23",
          "evidenceSummary": "Page 8 assessment overview: Paper 1 (01) is a 2-hour written paper with 100 marks, covering all syllabus content. Page 23 entry code table confirms component code 01 for Paper 1."
        }
      ],
      "reviewStatus": "codex-reviewed"
    },
    {
      "statementId": "OCR-6993-OFFICIAL-OCR-6993-CA8",
      "statementType": "assessable-content",
      "applicability": {
        "kind": "eligible",
        "papers": [
          "01"
        ]
      },
      "rationale": "Codex verified the statement tier against the official Paper tiers and the official assessment rule that the applicable syllabus content may be assessed on every Paper within that tier.",
      "sourceReferences": [
        {
          "sourceSha256": "d682352b907c422bd5d994153bd5440b3146913e92e9a7524148515109f8cb3f",
          "sourceUrl": "https://www.ocr.org.uk/Images/457916-specification-from-2018-.pdf",
          "locator": "page 8, page 23",
          "evidenceSummary": "Page 8 assessment overview: Paper 1 (01) is a 2-hour written paper with 100 marks, covering all syllabus content. Page 23 entry code table confirms component code 01 for Paper 1."
        }
      ],
      "reviewStatus": "codex-reviewed"
    },
    {
      "statementId": "OCR-6993-OFFICIAL-OCR-6993-CA9",
      "statementType": "assessable-content",
      "applicability": {
        "kind": "eligible",
        "papers": [
          "01"
        ]
      },
      "rationale": "Codex verified the statement tier against the official Paper tiers and the official assessment rule that the applicable syllabus content may be assessed on every Paper within that tier.",
      "sourceReferences": [
        {
          "sourceSha256": "d682352b907c422bd5d994153bd5440b3146913e92e9a7524148515109f8cb3f",
          "sourceUrl": "https://www.ocr.org.uk/Images/457916-specification-from-2018-.pdf",
          "locator": "page 8, page 23",
          "evidenceSummary": "Page 8 assessment overview: Paper 1 (01) is a 2-hour written paper with 100 marks, covering all syllabus content. Page 23 entry code table confirms component code 01 for Paper 1."
        }
      ],
      "reviewStatus": "codex-reviewed"
    },
    {
      "statementId": "OCR-6993-OFFICIAL-OCR-6993-NM1",
      "statementType": "assessable-content",
      "applicability": {
        "kind": "eligible",
        "papers": [
          "01"
        ]
      },
      "rationale": "Codex verified the statement tier against the official Paper tiers and the official assessment rule that the applicable syllabus content may be assessed on every Paper within that tier.",
      "sourceReferences": [
        {
          "sourceSha256": "d682352b907c422bd5d994153bd5440b3146913e92e9a7524148515109f8cb3f",
          "sourceUrl": "https://www.ocr.org.uk/Images/457916-specification-from-2018-.pdf",
          "locator": "page 8, page 23",
          "evidenceSummary": "Page 8 assessment overview: Paper 1 (01) is a 2-hour written paper with 100 marks, covering all syllabus content. Page 23 entry code table confirms component code 01 for Paper 1."
        }
      ],
      "reviewStatus": "codex-reviewed"
    },
    {
      "statementId": "OCR-6993-OFFICIAL-OCR-6993-NM2",
      "statementType": "assessable-content",
      "applicability": {
        "kind": "eligible",
        "papers": [
          "01"
        ]
      },
      "rationale": "Codex verified the statement tier against the official Paper tiers and the official assessment rule that the applicable syllabus content may be assessed on every Paper within that tier.",
      "sourceReferences": [
        {
          "sourceSha256": "d682352b907c422bd5d994153bd5440b3146913e92e9a7524148515109f8cb3f",
          "sourceUrl": "https://www.ocr.org.uk/Images/457916-specification-from-2018-.pdf",
          "locator": "page 8, page 23",
          "evidenceSummary": "Page 8 assessment overview: Paper 1 (01) is a 2-hour written paper with 100 marks, covering all syllabus content. Page 23 entry code table confirms component code 01 for Paper 1."
        }
      ],
      "reviewStatus": "codex-reviewed"
    },
    {
      "statementId": "OCR-6993-OFFICIAL-OCR-6993-NM3",
      "statementType": "assessable-content",
      "applicability": {
        "kind": "eligible",
        "papers": [
          "01"
        ]
      },
      "rationale": "Codex verified the statement tier against the official Paper tiers and the official assessment rule that the applicable syllabus content may be assessed on every Paper within that tier.",
      "sourceReferences": [
        {
          "sourceSha256": "d682352b907c422bd5d994153bd5440b3146913e92e9a7524148515109f8cb3f",
          "sourceUrl": "https://www.ocr.org.uk/Images/457916-specification-from-2018-.pdf",
          "locator": "page 8, page 23",
          "evidenceSummary": "Page 8 assessment overview: Paper 1 (01) is a 2-hour written paper with 100 marks, covering all syllabus content. Page 23 entry code table confirms component code 01 for Paper 1."
        }
      ],
      "reviewStatus": "codex-reviewed"
    },
    {
      "statementId": "OCR-6993-OFFICIAL-OCR-6993-NM4",
      "statementType": "assessable-content",
      "applicability": {
        "kind": "eligible",
        "papers": [
          "01"
        ]
      },
      "rationale": "Codex verified the statement tier against the official Paper tiers and the official assessment rule that the applicable syllabus content may be assessed on every Paper within that tier.",
      "sourceReferences": [
        {
          "sourceSha256": "d682352b907c422bd5d994153bd5440b3146913e92e9a7524148515109f8cb3f",
          "sourceUrl": "https://www.ocr.org.uk/Images/457916-specification-from-2018-.pdf",
          "locator": "page 8, page 23",
          "evidenceSummary": "Page 8 assessment overview: Paper 1 (01) is a 2-hour written paper with 100 marks, covering all syllabus content. Page 23 entry code table confirms component code 01 for Paper 1."
        }
      ],
      "reviewStatus": "codex-reviewed"
    },
    {
      "statementId": "OCR-6993-OFFICIAL-OCR-6993-NM5",
      "statementType": "assessable-content",
      "applicability": {
        "kind": "eligible",
        "papers": [
          "01"
        ]
      },
      "rationale": "Codex verified the statement tier against the official Paper tiers and the official assessment rule that the applicable syllabus content may be assessed on every Paper within that tier.",
      "sourceReferences": [
        {
          "sourceSha256": "d682352b907c422bd5d994153bd5440b3146913e92e9a7524148515109f8cb3f",
          "sourceUrl": "https://www.ocr.org.uk/Images/457916-specification-from-2018-.pdf",
          "locator": "page 8, page 23",
          "evidenceSummary": "Page 8 assessment overview: Paper 1 (01) is a 2-hour written paper with 100 marks, covering all syllabus content. Page 23 entry code table confirms component code 01 for Paper 1."
        }
      ],
      "reviewStatus": "codex-reviewed"
    },
    {
      "statementId": "OCR-6993-OFFICIAL-OCR-6993-NM6",
      "statementType": "assessable-content",
      "applicability": {
        "kind": "eligible",
        "papers": [
          "01"
        ]
      },
      "rationale": "Codex verified the statement tier against the official Paper tiers and the official assessment rule that the applicable syllabus content may be assessed on every Paper within that tier.",
      "sourceReferences": [
        {
          "sourceSha256": "d682352b907c422bd5d994153bd5440b3146913e92e9a7524148515109f8cb3f",
          "sourceUrl": "https://www.ocr.org.uk/Images/457916-specification-from-2018-.pdf",
          "locator": "page 8, page 23",
          "evidenceSummary": "Page 8 assessment overview: Paper 1 (01) is a 2-hour written paper with 100 marks, covering all syllabus content. Page 23 entry code table confirms component code 01 for Paper 1."
        }
      ],
      "reviewStatus": "codex-reviewed"
    },
    {
      "statementId": "OCR-6993-OFFICIAL-OCR-6993-NM7",
      "statementType": "assessable-content",
      "applicability": {
        "kind": "eligible",
        "papers": [
          "01"
        ]
      },
      "rationale": "Codex verified the statement tier against the official Paper tiers and the official assessment rule that the applicable syllabus content may be assessed on every Paper within that tier.",
      "sourceReferences": [
        {
          "sourceSha256": "d682352b907c422bd5d994153bd5440b3146913e92e9a7524148515109f8cb3f",
          "sourceUrl": "https://www.ocr.org.uk/Images/457916-specification-from-2018-.pdf",
          "locator": "page 8, page 23",
          "evidenceSummary": "Page 8 assessment overview: Paper 1 (01) is a 2-hour written paper with 100 marks, covering all syllabus content. Page 23 entry code table confirms component code 01 for Paper 1."
        }
      ],
      "reviewStatus": "codex-reviewed"
    },
    {
      "statementId": "OCR-6993-OFFICIAL-OCR-6993-NM8",
      "statementType": "assessable-content",
      "applicability": {
        "kind": "eligible",
        "papers": [
          "01"
        ]
      },
      "rationale": "Codex verified the statement tier against the official Paper tiers and the official assessment rule that the applicable syllabus content may be assessed on every Paper within that tier.",
      "sourceReferences": [
        {
          "sourceSha256": "d682352b907c422bd5d994153bd5440b3146913e92e9a7524148515109f8cb3f",
          "sourceUrl": "https://www.ocr.org.uk/Images/457916-specification-from-2018-.pdf",
          "locator": "page 8, page 23",
          "evidenceSummary": "Page 8 assessment overview: Paper 1 (01) is a 2-hour written paper with 100 marks, covering all syllabus content. Page 23 entry code table confirms component code 01 for Paper 1."
        }
      ],
      "reviewStatus": "codex-reviewed"
    },
    {
      "statementId": "OCR-6993-OFFICIAL-OCR-6993-NM9",
      "statementType": "assessment-objective",
      "applicability": {
        "kind": "not-specified"
      },
      "rationale": "The statement describes applying numerical methods in context, which is a general application skill rather than a precise mathematical concept. The underlying numerical methods are already covered by existing leaves.",
      "sourceReferences": [],
      "reviewStatus": "codex-reviewed"
    },
    {
      "statementId": "OCR-6993-OFFICIAL-OCR-6993-EL1",
      "statementType": "assessable-content",
      "applicability": {
        "kind": "eligible",
        "papers": [
          "01"
        ]
      },
      "rationale": "Codex verified the statement tier against the official Paper tiers and the official assessment rule that the applicable syllabus content may be assessed on every Paper within that tier.",
      "sourceReferences": [
        {
          "sourceSha256": "d682352b907c422bd5d994153bd5440b3146913e92e9a7524148515109f8cb3f",
          "sourceUrl": "https://www.ocr.org.uk/Images/457916-specification-from-2018-.pdf",
          "locator": "page 8, page 23",
          "evidenceSummary": "Page 8 assessment overview: Paper 1 (01) is a 2-hour written paper with 100 marks, covering all syllabus content. Page 23 entry code table confirms component code 01 for Paper 1."
        }
      ],
      "reviewStatus": "codex-reviewed"
    },
    {
      "statementId": "OCR-6993-OFFICIAL-OCR-6993-EL2",
      "statementType": "assessable-content",
      "applicability": {
        "kind": "eligible",
        "papers": [
          "01"
        ]
      },
      "rationale": "Codex verified the statement tier against the official Paper tiers and the official assessment rule that the applicable syllabus content may be assessed on every Paper within that tier.",
      "sourceReferences": [
        {
          "sourceSha256": "d682352b907c422bd5d994153bd5440b3146913e92e9a7524148515109f8cb3f",
          "sourceUrl": "https://www.ocr.org.uk/Images/457916-specification-from-2018-.pdf",
          "locator": "page 8, page 23",
          "evidenceSummary": "Page 8 assessment overview: Paper 1 (01) is a 2-hour written paper with 100 marks, covering all syllabus content. Page 23 entry code table confirms component code 01 for Paper 1."
        }
      ],
      "reviewStatus": "codex-reviewed"
    },
    {
      "statementId": "OCR-6993-OFFICIAL-OCR-6993-EL3",
      "statementType": "assessable-content",
      "applicability": {
        "kind": "eligible",
        "papers": [
          "01"
        ]
      },
      "rationale": "Codex verified the statement tier against the official Paper tiers and the official assessment rule that the applicable syllabus content may be assessed on every Paper within that tier.",
      "sourceReferences": [
        {
          "sourceSha256": "d682352b907c422bd5d994153bd5440b3146913e92e9a7524148515109f8cb3f",
          "sourceUrl": "https://www.ocr.org.uk/Images/457916-specification-from-2018-.pdf",
          "locator": "page 8, page 23",
          "evidenceSummary": "Page 8 assessment overview: Paper 1 (01) is a 2-hour written paper with 100 marks, covering all syllabus content. Page 23 entry code table confirms component code 01 for Paper 1."
        }
      ],
      "reviewStatus": "codex-reviewed"
    },
    {
      "statementId": "OCR-6993-OFFICIAL-OCR-6993-EL4",
      "statementType": "assessable-content",
      "applicability": {
        "kind": "eligible",
        "papers": [
          "01"
        ]
      },
      "rationale": "Codex verified the statement tier against the official Paper tiers and the official assessment rule that the applicable syllabus content may be assessed on every Paper within that tier.",
      "sourceReferences": [
        {
          "sourceSha256": "d682352b907c422bd5d994153bd5440b3146913e92e9a7524148515109f8cb3f",
          "sourceUrl": "https://www.ocr.org.uk/Images/457916-specification-from-2018-.pdf",
          "locator": "page 8, page 23",
          "evidenceSummary": "Page 8 assessment overview: Paper 1 (01) is a 2-hour written paper with 100 marks, covering all syllabus content. Page 23 entry code table confirms component code 01 for Paper 1."
        }
      ],
      "reviewStatus": "codex-reviewed"
    },
    {
      "statementId": "OCR-6993-OFFICIAL-OCR-6993-EL5",
      "statementType": "assessable-content",
      "applicability": {
        "kind": "eligible",
        "papers": [
          "01"
        ]
      },
      "rationale": "Codex verified the statement tier against the official Paper tiers and the official assessment rule that the applicable syllabus content may be assessed on every Paper within that tier.",
      "sourceReferences": [
        {
          "sourceSha256": "d682352b907c422bd5d994153bd5440b3146913e92e9a7524148515109f8cb3f",
          "sourceUrl": "https://www.ocr.org.uk/Images/457916-specification-from-2018-.pdf",
          "locator": "page 8, page 23",
          "evidenceSummary": "Page 8 assessment overview: Paper 1 (01) is a 2-hour written paper with 100 marks, covering all syllabus content. Page 23 entry code table confirms component code 01 for Paper 1."
        }
      ],
      "reviewStatus": "codex-reviewed"
    },
    {
      "statementId": "OCR-6993-OFFICIAL-OCR-6993-EL6",
      "statementType": "assessable-content",
      "applicability": {
        "kind": "eligible",
        "papers": [
          "01"
        ]
      },
      "rationale": "Codex verified the statement tier against the official Paper tiers and the official assessment rule that the applicable syllabus content may be assessed on every Paper within that tier.",
      "sourceReferences": [
        {
          "sourceSha256": "d682352b907c422bd5d994153bd5440b3146913e92e9a7524148515109f8cb3f",
          "sourceUrl": "https://www.ocr.org.uk/Images/457916-specification-from-2018-.pdf",
          "locator": "page 8, page 23",
          "evidenceSummary": "Page 8 assessment overview: Paper 1 (01) is a 2-hour written paper with 100 marks, covering all syllabus content. Page 23 entry code table confirms component code 01 for Paper 1."
        }
      ],
      "reviewStatus": "codex-reviewed"
    },
    {
      "statementId": "OCR-6993-OFFICIAL-OCR-6993-EL7",
      "statementType": "assessable-content",
      "applicability": {
        "kind": "eligible",
        "papers": [
          "01"
        ]
      },
      "rationale": "Codex verified the statement tier against the official Paper tiers and the official assessment rule that the applicable syllabus content may be assessed on every Paper within that tier.",
      "sourceReferences": [
        {
          "sourceSha256": "d682352b907c422bd5d994153bd5440b3146913e92e9a7524148515109f8cb3f",
          "sourceUrl": "https://www.ocr.org.uk/Images/457916-specification-from-2018-.pdf",
          "locator": "page 8, page 23",
          "evidenceSummary": "Page 8 assessment overview: Paper 1 (01) is a 2-hour written paper with 100 marks, covering all syllabus content. Page 23 entry code table confirms component code 01 for Paper 1."
        }
      ],
      "reviewStatus": "codex-reviewed"
    }
  ],
  "reviewStatus": "codex-reviewed",
  "calls": [
    {
      "label": "paper-applicability-baseline-OCR-6993",
      "provider": "local",
      "requestedModel": "local",
      "returnedModel": "local",
      "status": "local-only",
      "promptTokens": 0,
      "completionTokens": 0,
      "totalTokens": 0
    },
    {
      "label": "paper-applicability-codex-shared-review-OCR-6993",
      "provider": "local",
      "requestedModel": "local",
      "returnedModel": "local",
      "status": "local-only",
      "promptTokens": 0,
      "completionTokens": 0,
      "totalTokens": 0
    }
  ],
  "codexResidualResolution": {
    "correctionVersion": "knowledge-v5-residual-codex-resolution-1",
    "reviewedAt": "2026-07-20",
    "dispositionCount": 5
  },
  "codexResidualRound25": {
    "correctionVersion": "knowledge-v5-residual-round25-codex-1",
    "reviewedAt": "2026-07-20",
    "statementCount": 4
  },
  "leafClosureRound27": {
    "version": "knowledge-v5-leaf-closure-round27-1",
    "reviewedAt": "2026-07-20",
    "statementCount": 2
  },
  "sourceLocatorSynchronization": {
    "version": "knowledge-v5-coordinate-locator-sync-1",
    "synchronizedAt": "2026-07-19T18:34:19.270Z",
    "statementCount": 68
  }
}
