{
  "schemaVersion": "1.0.0",
  "key": "pearson-4ma1",
  "board": "Pearson Edexcel",
  "qualificationCode": "4MA1",
  "subjectCode": "4MA1",
  "qualificationName": "Pearson Edexcel International GCSE Mathematics A",
  "aliases": ["Edexcel-4MA1"],
  "sourcePageUrl": "https://qualifications.pearson.com/en/qualifications/edexcel-international-gcses/international-gcse-mathematics-a-2016.coursematerials.html#filterQuery=category:Pearson-UK:Category%2FExam-materials",
  "accessNote": "Pearson 的材料列表由页面动态加载，且部分最近试卷需要注册中心账号。第一版只提供官方材料入口，逐份链接通过候选审核后再发布。",
  "release": { "status": "approved", "approvedAt": "2026-07-16", "verifiedAt": "2026-07-16", "approvedBy": "human" },
  "assets": []
}
