{
  "board": "Edexcel",
  "program": "International A-Level Mathematics (IAL)",
  "specification_code": "XMA01 (IAS) / YMA01 (IAL)",
  "unit_codes": {
    "P1": "WMA11",
    "P2": "WMA12",
    "P3": "WMA13",
    "P4": "WMA14",
    "M1": "WME01",
    "M2": "WME02",
    "M3": "WME03",
    "S1": "WST01",
    "S2": "WST02",
    "S3": "WST03",
    "D1": "WDM01"
  },
  "first_teaching": "2018",
  "structure": "Modular - 14 units available, 6 units for full A-Level",
  "total_units": 14,
  "ias_requirement": "3 units (P1 + P2 + one applied)",
  "ial_requirement": "6 units (P1 + P2 + P3 + P4 + two applied)",
  "applied_options": [
    "M1 + S1",
    "M1 + M2",
    "M1 + D1",
    "S1 + D1",
    "S1 + S2"
  ],
  "units": [
    {
      "unit_id": "P1",
      "name": "Pure Mathematics 1",
      "duration": "1h 30m",
      "marks": 75,
      "weighting_ial": "16.7%",
      "weighting_ias": "33.3%"
    },
    {
      "unit_id": "P2",
      "name": "Pure Mathematics 2",
      "duration": "1h 30m",
      "marks": 75,
      "weighting_ial": "16.7%",
      "weighting_ias": "33.3%"
    },
    {
      "unit_id": "P3",
      "name": "Pure Mathematics 3",
      "duration": "1h 30m",
      "marks": 75,
      "weighting_ial": "16.7%",
      "weighting_ias": "N/A"
    },
    {
      "unit_id": "P4",
      "name": "Pure Mathematics 4",
      "duration": "1h 30m",
      "marks": 75,
      "weighting_ial": "16.7%",
      "weighting_ias": "N/A"
    },
    {
      "unit_id": "M1",
      "name": "Mechanics 1",
      "duration": "1h 30m",
      "marks": 75,
      "weighting_ial": "16.7%",
      "weighting_ias": "33.3%"
    },
    {
      "unit_id": "M2",
      "name": "Mechanics 2",
      "duration": "1h 30m",
      "marks": 75,
      "weighting_ial": "16.7%",
      "weighting_ias": "N/A"
    },
    {
      "unit_id": "M3",
      "name": "Mechanics 3",
      "duration": "1h 30m",
      "marks": 75,
      "weighting_ial": "16.7%",
      "weighting_ias": "N/A"
    },
    {
      "unit_id": "S1",
      "name": "Statistics 1",
      "duration": "1h 30m",
      "marks": 75,
      "weighting_ial": "16.7%",
      "weighting_ias": "33.3%"
    },
    {
      "unit_id": "S2",
      "name": "Statistics 2",
      "duration": "1h 30m",
      "marks": 75,
      "weighting_ial": "16.7%",
      "weighting_ias": "N/A"
    },
    {
      "unit_id": "S3",
      "name": "Statistics 3",
      "duration": "1h 30m",
      "marks": 75,
      "weighting_ial": "16.7%",
      "weighting_ias": "N/A"
    },
    {
      "unit_id": "D1",
      "name": "Decision Mathematics 1",
      "duration": "1h 30m",
      "marks": 75,
      "weighting_ial": "16.7%",
      "weighting_ias": "33.3%"
    }
  ],
  "topics": [
    {
      "topic_id": "P1.1",
      "name": "Algebra and Functions",
      "category": "Pure Mathematics 1",
      "unit": "P1",
      "subtopics": [
        "Laws of indices",
        "Surds",
        "Quadratic functions and graphs",
        "Solving quadratic equations",
        "Completing the square",
        "Polynomials and factor theorem",
        "Graphs of functions and transformations"
      ]
    },
    {
      "topic_id": "P1.2",
      "name": "Coordinate Geometry",
      "category": "Pure Mathematics 1",
      "unit": "P1",
      "subtopics": [
        "Equation of a straight line",
        "Gradient, parallel and perpendicular lines",
        "Equation of a circle",
        "Tangents and normals to circles"
      ]
    },
    {
      "topic_id": "P1.3",
      "name": "Trigonometry",
      "category": "Pure Mathematics 1",
      "unit": "P1",
      "subtopics": [
        "Sine, cosine and tangent ratios",
        "Exact trigonometric values",
        "Trigonometric graphs",
        "Sine rule and cosine rule",
        "Area of a triangle",
        "Solving trigonometric equations"
      ]
    },
    {
      "topic_id": "P1.4",
      "name": "Differentiation",
      "category": "Pure Mathematics 1",
      "unit": "P1",
      "subtopics": [
        "Differentiation of powers of x",
        "Tangents and normals",
        "Stationary points",
        "Optimisation"
      ]
    },
    {
      "topic_id": "P1.5",
      "name": "Integration",
      "category": "Pure Mathematics 1",
      "unit": "P1",
      "subtopics": [
        "Integration of powers of x",
        "Definite integrals",
        "Area under curves"
      ]
    },
    {
      "topic_id": "P2.1",
      "name": "Proof",
      "category": "Pure Mathematics 2",
      "unit": "P2",
      "subtopics": [
        "Proof by deduction",
        "Proof by exhaustion",
        "Disproof by counterexample"
      ]
    },
    {
      "topic_id": "P2.2",
      "name": "Algebra and Functions",
      "category": "Pure Mathematics 2",
      "unit": "P2",
      "subtopics": [
        "Modulus function",
        "Composite and inverse functions",
        "Transformations of graphs",
        "Partial fractions"
      ]
    },
    {
      "topic_id": "P2.3",
      "name": "Coordinate Geometry",
      "category": "Pure Mathematics 2",
      "unit": "P2",
      "subtopics": [
        "Parametric equations",
        "Parametric differentiation"
      ]
    },
    {
      "topic_id": "P2.4",
      "name": "Sequences and Series",
      "category": "Pure Mathematics 2",
      "unit": "P2",
      "subtopics": [
        "Binomial expansion for positive integer n",
        "Arithmetic sequences and series",
        "Geometric sequences and series",
        "Sum to infinity"
      ]
    },
    {
      "topic_id": "P2.5",
      "name": "Exponentials and Logarithms",
      "category": "Pure Mathematics 2",
      "unit": "P2",
      "subtopics": [
        "Laws of logarithms",
        "Exponential and logarithmic functions",
        "Modelling with exponentials (growth and decay)"
      ]
    },
    {
      "topic_id": "P2.6",
      "name": "Trigonometry",
      "category": "Pure Mathematics 2",
      "unit": "P2",
      "subtopics": [
        "Radians",
        "Arc length and sector area",
        "Reciprocal trigonometric functions",
        "Trigonometric identities",
        "Double angle formulae",
        "Compound angle formulae",
        "a sin x + b cos x form"
      ]
    },
    {
      "topic_id": "P2.7",
      "name": "Differentiation",
      "category": "Pure Mathematics 2",
      "unit": "P2",
      "subtopics": [
        "Chain rule",
        "Product rule",
        "Quotient rule",
        "Connected rates of change"
      ]
    },
    {
      "topic_id": "P2.8",
      "name": "Integration",
      "category": "Pure Mathematics 2",
      "unit": "P2",
      "subtopics": [
        "Integration by substitution",
        "Integration by parts",
        "Areas and volumes"
      ]
    },
    {
      "topic_id": "P3.1",
      "name": "Algebra and Functions",
      "category": "Pure Mathematics 3",
      "unit": "P3",
      "subtopics": [
        "Rational functions",
        "Partial fractions",
        "Modulus inequalities"
      ]
    },
    {
      "topic_id": "P3.2",
      "name": "Trigonometry",
      "category": "Pure Mathematics 3",
      "unit": "P3",
      "subtopics": [
        "Inverse trigonometric functions",
        "General solutions of trigonometric equations"
      ]
    },
    {
      "topic_id": "P3.3",
      "name": "Exponentials and Logarithms",
      "category": "Pure Mathematics 3",
      "unit": "P3",
      "subtopics": [
        "e^x and ln x",
        "Reduction to linear form"
      ]
    },
    {
      "topic_id": "P3.4",
      "name": "Differentiation",
      "category": "Pure Mathematics 3",
      "unit": "P3",
      "subtopics": [
        "Chain rule (including repeated application)",
        "Implicit differentiation",
        "Differentiation of inverse trigonometric functions"
      ]
    },
    {
      "topic_id": "P3.5",
      "name": "Integration",
      "category": "Pure Mathematics 3",
      "unit": "P3",
      "subtopics": [
        "Integration using partial fractions",
        "Integration of trigonometric powers",
        "Further substitution",
        "Further integration by parts"
      ]
    },
    {
      "topic_id": "P3.6",
      "name": "Numerical Methods",
      "category": "Pure Mathematics 3",
      "unit": "P3",
      "subtopics": [
        "Change of sign methods",
        "Iterative methods",
        "Newton-Raphson method"
      ]
    },
    {
      "topic_id": "P4.1",
      "name": "Proof",
      "category": "Pure Mathematics 4",
      "unit": "P4",
      "subtopics": [
        "Proof by contradiction"
      ]
    },
    {
      "topic_id": "P4.2",
      "name": "Algebra and Functions",
      "category": "Pure Mathematics 4",
      "unit": "P4",
      "subtopics": [
        "Binomial expansion for rational and negative indices",
        "Partial fractions (repeated factors)",
        "Maclaurin series"
      ]
    },
    {
      "topic_id": "P4.3",
      "name": "Differentiation",
      "category": "Pure Mathematics 4",
      "unit": "P4",
      "subtopics": [
        "Implicit differentiation (advanced)",
        "Parametric differentiation"
      ]
    },
    {
      "topic_id": "P4.4",
      "name": "Integration",
      "category": "Pure Mathematics 4",
      "unit": "P4",
      "subtopics": [
        "Differential equations (first order, separable)",
        "Using integrating factor"
      ]
    },
    {
      "topic_id": "P4.5",
      "name": "Vectors",
      "category": "Pure Mathematics 4",
      "unit": "P4",
      "subtopics": [
        "3D vectors",
        "Scalar (dot) product",
        "Vector equation of a line",
        "Angle between lines",
        "Shortest distance problems"
      ]
    },
    {
      "topic_id": "M1.1",
      "name": "Mathematical Modelling",
      "category": "Mechanics 1",
      "unit": "M1",
      "subtopics": [
        "Modelling assumptions",
        "Constructing a model"
      ]
    },
    {
      "topic_id": "M1.2",
      "name": "Vectors in Mechanics",
      "category": "Mechanics 1",
      "unit": "M1",
      "subtopics": [
        "Vector representation of forces and displacements",
        "Resultant vectors",
        "i-j notation"
      ]
    },
    {
      "topic_id": "M1.3",
      "name": "Kinematics",
      "category": "Mechanics 1",
      "unit": "M1",
      "subtopics": [
        "Displacement, velocity, acceleration",
        "suvat equations",
        "Velocity-time graphs",
        "Motion under gravity",
        "Projectiles"
      ]
    },
    {
      "topic_id": "M1.4",
      "name": "Newton's Laws",
      "category": "Mechanics 1",
      "unit": "M1",
      "subtopics": [
        "Newton's first, second and third laws",
        "Connected particles",
        "Pulleys",
        "Inclined planes"
      ]
    },
    {
      "topic_id": "M1.5",
      "name": "Momentum and Impulse",
      "category": "Mechanics 1",
      "unit": "M1",
      "subtopics": [
        "Momentum and impulse",
        "Conservation of momentum",
        "Direct impact (1D collisions)"
      ]
    },
    {
      "topic_id": "M1.6",
      "name": "Friction and Statics",
      "category": "Mechanics 1",
      "unit": "M1",
      "subtopics": [
        "Friction (limiting equilibrium)",
        "Coefficient of friction",
        "Ladder problems",
        "Moments and equilibrium"
      ]
    },
    {
      "topic_id": "S1.1",
      "name": "Data Representation",
      "category": "Statistics 1",
      "unit": "S1",
      "subtopics": [
        "Histograms",
        "Stem and leaf diagrams",
        "Box plots",
        "Cumulative frequency"
      ]
    },
    {
      "topic_id": "S1.2",
      "name": "Measures of Location and Dispersion",
      "category": "Statistics 1",
      "unit": "S1",
      "subtopics": [
        "Mean, median, mode",
        "Range, IQR, variance, standard deviation",
        "Linear interpolation",
        "Outliers",
        "Coding"
      ]
    },
    {
      "topic_id": "S1.3",
      "name": "Probability",
      "category": "Statistics 1",
      "unit": "S1",
      "subtopics": [
        "Basic probability",
        "Venn diagrams",
        "Mutually exclusive and independent events",
        "Tree diagrams",
        "Conditional probability"
      ]
    },
    {
      "topic_id": "S1.4",
      "name": "Correlation and Regression",
      "category": "Statistics 1",
      "unit": "S1",
      "subtopics": [
        "Scatter diagrams",
        "Pearson's product moment correlation coefficient",
        "Regression lines",
        "Interpolation and extrapolation"
      ]
    },
    {
      "topic_id": "S1.5",
      "name": "Discrete Random Variables",
      "category": "Statistics 1",
      "unit": "S1",
      "subtopics": [
        "Probability distributions",
        "Expectation and variance"
      ]
    },
    {
      "topic_id": "S1.6",
      "name": "The Normal Distribution",
      "category": "Statistics 1",
      "unit": "S1",
      "subtopics": [
        "Standard normal distribution (Z)",
        "Finding probabilities",
        "Finding critical values",
        "Normal approximation to binomial"
      ]
    }
  ]
}